predictions_analyzer/__init__.py
predictions_analyzer/analyze.py
predictions_analyzer/base.py
predictions_analyzer/cluster.py
predictions_analyzer/encodings.py
predictions_analyzer/ensemble.py
predictions_analyzer/hyper_tune.py
predictions_analyzer/losses.py
predictions_analyzer/meta_predictor.py
predictions_analyzer/models.py
predictions_analyzer/nn.py
predictions_analyzer/optuna.py
predictions_analyzer/segmentation_analysis.py
predictions_analyzer/sequence.py
predictions_analyzer/tabular.py
predictions_analyzer/validation.py
predictions_analyzer/vision.py
predictions_analyzer/wandb_local.py
tests/__init__.py
tests/test_analyze.py
tests/test_base.py
tests/test_encodings.py
tests/test_ensemble.py
tests/test_losses.py
tests/test_meta_predictor.py
tests/test_segmentation_analysis.py
tests/test_tabular.py
predictions_analyzer-0.0.55.dist-info/LICENSE
predictions_analyzer-0.0.55.dist-info/METADATA
predictions_analyzer-0.0.55.dist-info/WHEEL
predictions_analyzer-0.0.55.dist-info/top_level.txt
predictions_analyzer-0.0.55.dist-info/RECORD
