Metadata-Version: 2.1
Name: predictions-analyzer
Version: 0.0.55
Summary: A powerful tool for analyzing and ensembling predictions
Home-page: https://github.com/ThomasMeli/predictions_analyzer
Author: Thomas Meli
Author-email: tpmeli.data@gmail.com
License: UNKNOWN
Platform: UNKNOWN
Classifier: Programming Language :: Python :: 3
Classifier: License :: OSI Approved :: MIT License
Classifier: Operating System :: OS Independent
Requires-Python: >=3.7
